FIFO_Buffer/fifo.v
module fifo_single_clock(fifo_cntr_reg, empty_reg, full_reg, buf_out, buf_in, rst, wr, rd, clk);
	input wire clk, rst, rd, wr ;
	input wire [7:0] buf_in ;
	output reg [7:0] buf_out ;
	output reg [6:0] fifo_cntr_reg ; // should count from 0 to 64
	output reg empty_reg, full_reg ;
	
	wire rd_en, wr_en;
	reg [7:0] buf_mem [63:0] ; // 8 bit words in 64
	reg [5:0] rd_ptr_reg, wr_ptr_reg;
	reg [5:0] rd_ptr_next, wr_ptr_next;
	reg empty_next, full_next;
	reg [6:0] fifo_cntr_next;
	
	assign rd_en = (~empty_reg) & rd;
	assign wr_en = (~full_reg) & wr;
	
	always @(posedge clk, posedge rst)
		begin
		if(rst)
			begin
			empty_reg <= 1'b1;
			full_reg <= 1'b0;
			rd_ptr_reg <= 0;
			wr_ptr_reg <= 0;
			fifo_cntr_reg <= 0;
			end
		else
			begin
			empty_reg <= empty_next;
			full_reg <= full_next;
			rd_ptr_reg <= rd_ptr_next;
			wr_ptr_reg <= wr_ptr_next;
			fifo_cntr_reg <= fifo_cntr_next;
			end
		end	
	
	always @(posedge clk)
		begin
		if(wr_en & rd_en)
			begin
			buf_mem[wr_ptr_reg] <= buf_in;
			buf_out <= buf_mem[rd_ptr_reg];
			end
		else if(wr_en)
			begin
			buf_mem[wr_ptr_reg] <= buf_in;
			buf_out <= {(8){1'bz}};
			end
		else if(rd_en)
			begin
			buf_out <= buf_mem[rd_ptr_reg];
			end
		else
			begin
			buf_out <= {(8){1'bz}};
			end
		end
	always @(*)
		begin
		empty_next = empty_reg ;
		full_next = full_reg;
		rd_ptr_next = rd_ptr_reg;
		wr_ptr_next = wr_ptr_reg;
		fifo_cntr_next = fifo_cntr_reg;
		case({rd,wr})
			2'b01:
				begin
				if(~full_reg)
					begin
					empty_next = 1'b0 ;
					fifo_cntr_next = fifo_cntr_reg + 1;
					full_next = (fifo_cntr_next == 64);
					rd_ptr_next = rd_ptr_reg;
					wr_ptr_next = wr_ptr_reg + 1;
					end
				end
			2'b10:
				begin
				if(~empty_reg)
					begin
					full_next = 1'b0;
					fifo_cntr_next = fifo_cntr_reg - 1;
					empty_next = (fifo_cntr_next == 0);
					rd_ptr_next = rd_ptr_reg + 1;
					wr_ptr_next = wr_ptr_reg;
					end
				end
			2'b11:
				begin
				if(~empty_reg & ~full_reg)
					begin
					rd_ptr_next = rd_ptr_reg + 1;
					wr_ptr_next = wr_ptr_reg + 1;
					end
				end
		endcase
		end
	endmodule

FIFO_Buffer/test_fifo.v
module test_fifo();
	reg clk, rst, rd, wr;
	reg [7:0] buf_in;
	wire empty, full;
	wire [7:0] buf_out;
	wire [6:0] fifo_cntr;
	integer i;
	
	fifo_single_clock A(fifo_cntr,empty,full,buf_out,buf_in,rst,wr,rd,clk);
	
	always #5 clk = ~clk;
	
	initial 
		begin
		for(i = 0; i< 30; i = i + 1)
			begin
			@(negedge clk);
			buf_in = i ;
			end
		buf_in = 8'd0;
		repeat(7) @(negedge clk);
		for(i = 30; i < 69; i = i + 1)
			begin
			@(negedge clk);
			buf_in = i;
			end
		end
		
	
	
	initial 
		begin
		clk = 1'b0;
		rst = 1'b1;
		rd = 1'b0;
		wr = 1'b0;
		@(negedge clk);
		rst = 1'b0;
		wr = 1'b1;
		repeat(29) @(negedge clk);
		wr = 1'b0;
		rd = 1'b1;
		repeat(5) @(negedge clk);
		wr  = 1'b1;
		repeat(2) @(negedge clk);
		rd = 1'b0;
		repeat(45) @(negedge clk);
		wr=1'b0;
		rst = 1'b1;
		@(negedge clk);
		#3 $finish;
		end
	initial
		begin
		$dumpfile("fifo.vcd");
		$dumpvars(0,test_fifo);
		end
endmodule

FIFO_Buffer/fifo.vcd
$date
	Fri Jan 01 14:38:58 2021
$end
$version
	Icarus Verilog
$end
$timescale
	1s
$end
$scope module test_fifo $end
$var wire 1 ! full $end
$var wire 7 " fifo_cntr [6:0] $end
$var wire 1 # empty $end
$var wire 8 $ buf_out [7:0] $end
$var reg 8 % buf_in [7:0] $end
$var reg 1 & clk $end
$var reg 1 ' rd $end
$var reg 1 ( rst $end
$var reg 1 ) wr $end
$var integer 32 * i [31:0] $end
$scope module A $end
$var wire 8 + buf_in [7:0] $end
$var wire 1 & clk $end
$var wire 1 ' rd $end
$var wire 1 , rd_en $end
$var wire 1 ( rst $end
$var wire 1 ) wr $end
$var wire 1 - wr_en $end
$var reg 8 . buf_out [7:0] $end
$var reg 1 / empty_next $end
$var reg 1 # empty_reg $end
$var reg 7 0 fifo_cntr_next [6:0] $end
$var reg 7 1 fifo_cntr_reg [6:0] $end
$var reg 1 2 full_next $end
$var reg 1 ! full_reg $end
$var reg 6 3 rd_ptr_next [5:0] $end
$var reg 6 4 rd_ptr_reg [5:0] $end
$var reg 6 5 wr_ptr_next [5:0] $end
$var reg 6 6 wr_ptr_reg [5:0] $end
$upscope $end
$upscope $end
$enddefinitions $end
#0
$dumpvars
b0 6
b0 5
b0 4
b0 3
02
b0 1
b0 0
1/
bx .
0-
0,
b0 +
b1 *
0)
1(
0'
0&
b0 %
bx $
1#
b0 "
0!
$end
#5
bz $
bz .
1&
#10
1-
b1 5
b1 0
0/
1)
0(
b10 *
b1 %
b1 +
0&
#15
b10 5
b10 0
b1 "
b1 1
b1 6
0#
1&
#20
b11 *
b10 %
b10 +
0&
#25
b11 5
b11 0
b10 "
b10 1
b10 6
1&
#30
b100 *
b11 %
b11 +
0&
#35
b100 5
b100 0
b11 "
b11 1
b11 6
1&
#40
b101 *
b100 %
b100 +
0&
#45
b101 5
b101 0
b100 "
b100 1
b100 6
1&
#50
b110 *
b101 %
b101 +
0&
#55
b110 5
b110 0
b101 "
b101 1
b101 6
1&
#60
b111 *
b110 %
b110 +
0&
#65
b111 5
b111 0
b110 "
b110 1
b110 6
1&
#70
b1000 *
b111 %
b111 +
0&
#75
b1000 5
b1000 0
b111 "
b111 1
b111 6
1&
#80
b1001 *
b1000 %
b1000 +
0&
#85
b1001 5
b1001 0
b1000 "
b1000 1
b1000 6
1&
#90
b1010 *
b1001 %
b1001 +
0&
#95
b1010 5
b1010 0
b1001 "
b1001 1
b1001 6
1&
#100
b1011 *
b1010 %
b1010 +
0&
#105
b1011 5
b1011 0
b1010 "
b1010 1
b1010 6
1&
#110
b1100 *
b1011 %
b1011 +
0&
#115
b1100 5
b1100 0
b1011 "
b1011 1
b1011 6
1&
#120
b1101 *
b1100 %
b1100 +
0&
#125
b1101 5
b1101 0
b1100 "
b1100 1
b1100 6
1&
#130
b1110 *
b1101 %
b1101 +
0&
#135
b1110 5
b1110 0
b1101 "
b1101 1
b1101 6
1&
#140
b1111 *
b1110 %
b1110 +
0&
#145
b1111 5
b1111 0
b1110 "
b1110 1
b1110 6
1&
#150
b10000 *
b1111 %
b1111 +
0&
#155
b10000 5
b10000 0
b1111 "
b1111 1
b1111 6
1&
#160
b10001 *
b10000 %
b10000 +
0&
#165
b10001 5
b10001 0
b10000 "
b10000 1
b10000 6
1&
#170
b10010 *
b10001 %
b10001 +
0&
#175
b10010 5
b10010 0
b10001 "
b10001 1
b10001 6
1&
#180
b10011 *
b10010 %
b10010 +
0&
#185
b10011 5
b10011 0
b10010 "
b10010 1
b10010 6
1&
#190
b10100 *
b10011 %
b10011 +
0&
#195
b10100 5
b10100 0
b10011 "
b10011 1
b10011 6
1&
#200
b10101 *
b10100 %
b10100 +
0&
#205
b10101 5
b10101 0
b10100 "
b10100 1
b10100 6
1&
#210
b10110 *
b10101 %
b10101 +
0&
#215
b10110 5
b10110 0
b10101 "
b10101 1
b10101 6
1&
#220
b10111 *
b10110 %
b10110 +
0&
#225
b10111 5
b10111 0
b10110 "
b10110 1
b10110 6
1&
#230
b11000 *
b10111 %
b10111 +
0&
#235
b11000 5
b11000 0
b10111 "
b10111 1
b10111 6
1&
#240
b11001 *
b11000 %
b11000 +
0&
#245
b11001 5
b11001 0
b11000 "
b11000 1
b11000 6
1&
#250
b11010 *
b11001 %
b11001 +
0&
#255
b11010 5
b11010 0
b11001 "
b11001 1
b11001 6
1&
#260
b11011 *
b11010 %
b11010 +
0&
#265
b11011 5
b11011 0
b11010 "
b11010 1
b11010 6
1&
#270
b11100 *
b11011 %
b11011 +
0&
#275
b11100 5
b11100 0
b11011 "
b11011 1
b11011 6
1&
#280
b11101 *
b11100 %
b11100 +
0&
#285
b11101 5
b11101 0
b11100 "
b11100 1
b11100 6
1&
#290
b11110 *
b0 %
b0 +
0&
#295
b11110 5
b11110 0
b11101 "
b11101 1
b11101 6
1&
#300
1,
0-
b1 3
b11100 0
b11101 5
1'
0)
0&
#305
b10 3
b11011 0
b1 $
b1 .
b11100 "
b11100 1
b1 4
1&
#310
0&
#315
b11 3
b11010 0
b10 $
b10 .
b11011 "
b11011 1
b10 4
1&
#320
0&
#325
b100 3
b11001 0
b11 $
b11 .
b11010 "
b11010 1
b11 4
1&
#330
0&
#335
b101 3
b11000 0
b100 $
b100 .
b11001 "
b11001 1
b100 4
1&
#340
0&
#345
b110 3
b10111 0
b101 $
b101 .
b11000 "
b11000 1
b101 4
1&
#350
1-
b11110 5
b11000 0
b110 3
1)
0&
#355
b11111 5
b111 3
b110 $
b110 .
b11110 6
b110 4
1&
#360
0&
#365
b100000 5
b1000 3
b111 $
b111 .
b11111 6
b111 4
1&
#370
0,
b11001 0
b100000 5
b111 3
0'
b11111 *
b11110 %
b11110 +
0&
#375
b100001 5
b11010 0
bz $
bz .
b11001 "
b11001 1
b100000 6
1&
#380
b100000 *
b11111 %
b11111 +
0&
#385
b100010 5
b11011 0
b11010 "
b11010 1
b100001 6
1&
#390
b100001 *
b100000 %
b100000 +
0&
#395
b100011 5
b11100 0
b11011 "
b11011 1
b100010 6
1&
#400
b100010 *
b100001 %
b100001 +
0&
#405
b100100 5
b11101 0
b11100 "
b11100 1
b100011 6
1&
#410
b100011 *
b100010 %
b100010 +
0&
#415
b100101 5
b11110 0
b11101 "
b11101 1
b100100 6
1&
#420
b100100 *
b100011 %
b100011 +
0&
#425
b100110 5
b11111 0
b11110 "
b11110 1
b100101 6
1&
#430
b100101 *
b100100 %
b100100 +
0&
#435
b100111 5
b100000 0
b11111 "
b11111 1
b100110 6
1&
#440
b100110 *
b100101 %
b100101 +
0&
#445
b101000 5
b100001 0
b100000 "
b100000 1
b100111 6
1&
#450
b100111 *
b100110 %
b100110 +
0&
#455
b101001 5
b100010 0
b100001 "
b100001 1
b101000 6
1&
#460
b101000 *
b100111 %
b100111 +
0&
#465
b101010 5
b100011 0
b100010 "
b100010 1
b101001 6
1&
#470
b101001 *
b101000 %
b101000 +
0&
#475
b101011 5
b100100 0
b100011 "
b100011 1
b101010 6
1&
#480
b101010 *
b101001 %
b101001 +
0&
#485
b101100 5
b100101 0
b100100 "
b100100 1
b101011 6
1&
#490
b101011 *
b101010 %
b101010 +
0&
#495
b101101 5
b100110 0
b100101 "
b100101 1
b101100 6
1&
#500
b101100 *
b101011 %
b101011 +
0&
#505
b101110 5
b100111 0
b100110 "
b100110 1
b101101 6
1&
#510
b101101 *
b101100 %
b101100 +
0&
#515
b101111 5
b101000 0
b100111 "
b100111 1
b101110 6
1&
#520
b101110 *
b101101 %
b101101 +
0&
#525
b110000 5
b101001 0
b101000 "
b101000 1
b101111 6
1&
#530
b101111 *
b101110 %
b101110 +
0&
#535
b110001 5
b101010 0
b101001 "
b101001 1
b110000 6
1&
#540
b110000 *
b101111 %
b101111 +
0&
#545
b110010 5
b101011 0
b101010 "
b101010 1
b110001 6
1&
#550
b110001 *
b110000 %
b110000 +
0&
#555
b110011 5
b101100 0
b101011 "
b101011 1
b110010 6
1&
#560
b110010 *
b110001 %
b110001 +
0&
#565
b110100 5
b101101 0
b101100 "
b101100 1
b110011 6
1&
#570
b110011 *
b110010 %
b110010 +
0&
#575
b110101 5
b101110 0
b101101 "
b101101 1
b110100 6
1&
#580
b110100 *
b110011 %
b110011 +
0&
#585
b110110 5
b101111 0
b101110 "
b101110 1
b110101 6
1&
#590
b110101 *
b110100 %
b110100 +
0&
#595
b110111 5
b110000 0
b101111 "
b101111 1
b110110 6
1&
#600
b110110 *
b110101 %
b110101 +
0&
#605
b111000 5
b110001 0
b110000 "
b110000 1
b110111 6
1&
#610
b110111 *
b110110 %
b110110 +
0&
#615
b111001 5
b110010 0
b110001 "
b110001 1
b111000 6
1&
#620
b111000 *
b110111 %
b110111 +
0&
#625
b111010 5
b110011 0
b110010 "
b110010 1
b111001 6
1&
#630
b111001 *
b111000 %
b111000 +
0&
#635
b111011 5
b110100 0
b110011 "
b110011 1
b111010 6
1&
#640
b111010 *
b111001 %
b111001 +
0&
#645
b111100 5
b110101 0
b110100 "
b110100 1
b111011 6
1&
#650
b111011 *
b111010 %
b111010 +
0&
#655
b111101 5
b110110 0
b110101 "
b110101 1
b111100 6
1&
#660
b111100 *
b111011 %
b111011 +
0&
#665
b111110 5
b110111 0
b110110 "
b110110 1
b111101 6
1&
#670
b111101 *
b111100 %
b111100 +
0&
#675
b111111 5
b111000 0
b110111 "
b110111 1
b111110 6
1&
#680
b111110 *
b111101 %
b111101 +
0&
#685
b0 5
b111001 0
b111000 "
b111000 1
b111111 6
1&
#690
b111111 *
b111110 %
b111110 +
0&
#695
b1 5
b111010 0
b111001 "
b111001 1
b0 6
1&
#700
b1000000 *
b111111 %
b111111 +
0&
#705
b10 5
b111011 0
b111010 "
b111010 1
b1 6
1&
#710
b1000001 *
b1000000 %
b1000000 +
0&
#715
b11 5
b111100 0
b111011 "
b111011 1
b10 6
1&
#720
b1000010 *
b1000001 %
b1000001 +
0&
#725
b100 5
b111101 0
b111100 "
b111100 1
b11 6
1&
#730
b1000011 *
b1000010 %
b1000010 +
0&
#735
b101 5
b111110 0
b111101 "
b111101 1
b100 6
1&
#740
b1000100 *
b1000011 %
b1000011 +
0&
#745
b110 5
b111111 0
b111110 "
b111110 1
b101 6
1&
#750
b1000101 *
b1000100 %
b1000100 +
0&
#755
b111 5
12
b1000000 0
b111111 "
b111111 1
b110 6
1&
#760
0&
#765
0-
b1000000 "
b1000000 1
b111 6
1!
1&
#770
0&
#775
1&
#780
0&
#785
1&
#790
0&
#795
1&
#800
0&
#805
1&
#810
0&
#815
1&
#820
b0 0
b0 5
b0 3
02
1/
b0 "
b0 1
b0 6
b0 4
0!
1#
1(
0)
0&
