Dff/free_shift_reg.v
module free_shift_reg
	#(parameter N = 8)
	(
		input wire clk, rst,
		input wire serial_in,
		output wire serial_out
	);
	
	reg [N-1 : 0] r_reg; 
	wire [N-1 : 0] r_next;
	
	always @(posedge clk)
		r_reg <= r_next ;
	
	assign r_next = rst? 0:{serial_in,r_reg[N-1:1]} ;
	assign serial_out = r_reg[0] ;
endmodule

Dff/test_shift_reg.v
module test_fsr();

	reg clk, rst, serial_in;
	wire serial_out ;
	
	free_shift_reg A(clk, rst, serial_in, serial_out);
	
	always #5 clk = ~clk ;
	
	initial begin
		clk = 1'b0 ;
		serial_in = 1'b1;
		rst = 1'b1 ;
		
		#77 rst = 1'b 0;
		
		#35 serial_in = 1'b0 ;
		
		#500 $finish ;
	end
	
	initial begin
		$dumpfile("free_shift_reg.vcd"); $dumpvars(0,test_fsr);
	end
endmodule

Dff/free_shift_reg.vcd
$date
	Wed Dec 30 18:35:39 2020
$end
$version
	Icarus Verilog
$end
$timescale
	1s
$end
$scope module test_fsr $end
$var wire 1 ! serial_out $end
$var reg 1 " clk $end
$var reg 1 # rst $end
$var reg 1 $ serial_in $end
$scope module A $end
$var wire 1 " clk $end
$var wire 1 # rst $end
$var wire 1 $ serial_in $end
$var wire 1 ! serial_out $end
$var wire 8 % r_next [7:0] $end
$var reg 8 & r_reg [7:0] $end
$upscope $end
$upscope $end
$enddefinitions $end
#0
$dumpvars
bx &
b0 %
1$
1#
0"
x!
$end
#5
0!
b0 &
1"
#10
0"
#15
1"
#20
0"
#25
1"
#30
0"
#35
1"
#40
0"
#45
1"
#50
0"
#55
1"
#60
0"
#65
1"
#70
0"
#75
1"
#77
b10000000 %
0#
#80
0"
#85
b11000000 %
b10000000 &
1"
#90
0"
#95
b11100000 %
b11000000 &
1"
#100
0"
#105
b11110000 %
b11100000 &
1"
#110
0"
#112
b1110000 %
0$
#115
b111000 %
b1110000 &
1"
#120
0"
#125
b11100 %
b111000 &
1"
#130
0"
#135
b1110 %
b11100 &
1"
#140
0"
#145
b111 %
b1110 &
1"
#150
0"
#155
b11 %
1!
b111 &
1"
#160
0"
#165
b1 %
b11 &
1"
#170
0"
#175
b0 %
b1 &
1"
#180
0"
#185
0!
b0 &
1"
