mul_1/mul1_cp.v
module mul1_cp(ldA,ldB,ldP,clrP,decB,done,eqz,start,clk,reset);
	input start,clk,eqz,reset;
	output reg ldA,ldB,ldP,clrP,decB,done;
	
	reg [2:0] PS,NS;
	parameter S0=3'b000, S1=3'b001, S2=3'b010, S3=3'b011, S4=3'b100, S5=3'b101, S6=3'b110, S7=3'b111 ;
	
	always @(posedge clk)
		begin
			#1
			if(reset) PS <= S0; 
			else PS <= NS;
		end
	
	always @(PS,eqz,start)
		begin
			case(PS)
				S0:
					begin
						#1 ldA = 0; ldB = 0; ldP = 0; clrP = 0; decB = 0; done = 0;
						#1 NS = start ? S1 : S0 ;
					end
				S1: 
					begin
						#1 ldA = 1;
						NS = S2;
					end	
				S2:
					begin
						#1 ldA = 0; ldB = 1; clrP = 1;
						NS = S3;
					end
				S3: 
					begin
						#1 ldB = 0; clrP = 0; ldP = 1; decB = 1;
						NS = eqz ? S4 : S3 ;
					end
				S4:
					begin
						#1 done = 1; ldP = 0; decB = 0;
						NS = S4;
					end
				S5:
					begin
						#1 ldA = 0; ldB = 0; ldP = 0; clrP = 0; decB = 0; done = 0;
						NS = S0;
					end
				S6: 
					begin
						#1 ldA = 0; ldB = 0; ldP = 0; clrP = 0; decB = 0; done = 0;
						NS = S0;
					end
				S7: 
					begin
						#1 ldA = 0; ldB = 0; ldP = 0; clrP = 0; decB = 0; done = 0;
						NS = S0;
					end
				default: 
					begin
					#1 ldA = 0; ldB = 0; ldP = 0; clrP = 0; decB = 0; done = 0;
					NS = S0;
					end
			endcase
		end
endmodule

mul_1/COMP.v
module COMP(eqz, d_in);
	input [15:0] d_in;
	output eqz;
	
	assign eqz = ~(|d_in);
	
endmodule

mul_1/ADD.v
module ADD(out,in1,in2);
	input [15:0] in1,in2;
	output [15:0] out;
	
	assign out = in1 + in2;
	
endmodule

mul_1/CNTR.v
module CNTR(d_out,d_in,ld,dec,clk);
	input ld,dec,clk;
	input [15:0] d_in;
	output reg [15:0] d_out;
	
	always @(posedge clk)
		begin
			if(ld)
				begin
					d_out <= d_in;
				end
			else if(dec)
				begin
					d_out <= d_out - 1;
				end
		end
endmodule

mul_1/pipo2.v
module PIPO2(d_out,d_in,ld,clr,clk);
	input ld,clr,clk;
	input [15:0] d_in;
	output reg [15:0] d_out;
	
	always @(posedge clk)
		begin
			if(clr)
				begin
					d_out <= 16'b0 ;
				end
			else if(ld)
				begin
					d_out <= d_in;
				end
		end
endmodule

mul_1/pipo1.v
module PIPO1(d_out,d_in,ld,clk);
	input  ld, clk;
	input [15:0] d_in;
	output reg [15:0] d_out;
	
	always @(posedge clk)
		begin
			if(ld)
				begin
					d_out <= d_in ;
				end
		end
endmodule

mul_1/mul1_dp.v
module mul1_dp(eqz,ldA,ldB,ldP,clrP,decB,d_in,clk);
	output eqz;
	input ldA,ldB,ldP,clrP,decB,clk;
	input [15:0] d_in;
	
	wire [15:0] bus, X, Y, Z, Bout;
	assign bus = d_in;
	
	PIPO1 A (X,bus,ldA,clk);
	PIPO2 P (Y,bus,ldP,clrP,clk);
	CNTR B (Bout,bus,ldB,decB,clk);
	ADD AD (Z,X,Y);
	COMP EQZ(eqz,Bout);
endmodule

mul_1/test_mul1.v
module test_mul1();

	reg [15:0] d_in;
	reg start, clk, reset;
	wire done, eqz, ldA, ldB, decB, clrP, ldP;
	
	mul1_dp dp(eqz,ldA,ldB,ldP,clrP,decB,d_in,clk);
	mul1_cp cp(ldA,ldB,ldP,clrP,decB,done,eqz,start,clk,reset);
	
	initial begin
		clk = 1'b0;
		reset = 1'b1;
		#7 reset = 1'b0;
		#3 start = 1'b1;
		#1000 $finish;
	end
	
	always #5 clk = ~clk ;
	
	initial begin
		#10 d_in = 17;
		#17 d_in = 5;
	end
	
	initial begin
		$dumpfile("mul1.vcd"); $dumpvars(0,test_mul1);
		$monitor($time," %d %b %d", dp.Y, done, cp.PS);
	end
	
endmodule

mul_1/mul1.vcd
$date
	Mon Dec 28 18:26:01 2020
$end
$version
	Icarus Verilog
$end
$timescale
	1s
$end
$scope module test_mul1 $end
$var wire 1 ! ldP $end
$var wire 1 " ldB $end
$var wire 1 # ldA $end
$var wire 1 $ eqz $end
$var wire 1 % done $end
$var wire 1 & decB $end
$var wire 1 ' clrP $end
$var reg 1 ( clk $end
$var reg 16 ) d_in [15:0] $end
$var reg 1 * reset $end
$var reg 1 + start $end
$scope module cp $end
$var wire 1 ( clk $end
$var wire 1 * reset $end
$var wire 1 + start $end
$var wire 1 $ eqz $end
$var reg 3 , NS [2:0] $end
$var reg 3 - PS [2:0] $end
$var reg 1 ' clrP $end
$var reg 1 & decB $end
$var reg 1 % done $end
$var reg 1 # ldA $end
$var reg 1 " ldB $end
$var reg 1 ! ldP $end
$upscope $end
$scope module dp $end
$var wire 16 . bus [15:0] $end
$var wire 1 ( clk $end
$var wire 1 ' clrP $end
$var wire 16 / d_in [15:0] $end
$var wire 1 & decB $end
$var wire 1 # ldA $end
$var wire 1 " ldB $end
$var wire 1 ! ldP $end
$var wire 1 $ eqz $end
$var wire 16 0 Z [15:0] $end
$var wire 16 1 Y [15:0] $end
$var wire 16 2 X [15:0] $end
$var wire 16 3 Bout [15:0] $end
$scope module A $end
$var wire 1 ( clk $end
$var wire 16 4 d_in [15:0] $end
$var wire 1 # ld $end
$var reg 16 5 d_out [15:0] $end
$upscope $end
$scope module AD $end
$var wire 16 6 in1 [15:0] $end
$var wire 16 7 out [15:0] $end
$var wire 16 8 in2 [15:0] $end
$upscope $end
$scope module B $end
$var wire 1 ( clk $end
$var wire 16 9 d_in [15:0] $end
$var wire 1 & dec $end
$var wire 1 " ld $end
$var reg 16 : d_out [15:0] $end
$upscope $end
$scope module EQZ $end
$var wire 16 ; d_in [15:0] $end
$var wire 1 $ eqz $end
$upscope $end
$scope module P $end
$var wire 1 ( clk $end
$var wire 1 ' clr $end
$var wire 16 < d_in [15:0] $end
$var wire 1 ! ld $end
$var reg 16 = d_out [15:0] $end
$upscope $end
$upscope $end
$upscope $end
$enddefinitions $end
#0
$dumpvars
bx =
bx <
bx ;
bx :
bx 9
bx 8
bx 7
bx 6
bx 5
bx 4
bx 3
bx 2
bx 1
bx 0
bx /
bx .
bx -
bx ,
x+
1*
bx )
0(
x'
x&
x%
x$
x#
x"
x!
$end
#5
1(
#6
b0 -
#7
0%
0&
0'
0!
0"
0#
0*
#8
b0x ,
#10
1+
0(
b10001 .
b10001 4
b10001 9
b10001 <
b10001 )
b10001 /
#12
b1 ,
#15
1(
#16
b1 -
#17
b10 ,
1#
#20
0(
#25
b10001 2
b10001 5
b10001 6
1(
#26
b10 -
#27
b11 ,
1'
1"
0#
b101 .
b101 4
b101 9
b101 <
b101 )
b101 /
#30
0(
#35
0$
b101 3
b101 :
b101 ;
b10001 0
b10001 7
b0 1
b0 8
b0 =
1(
#36
b11 -
#37
1&
1!
0'
0"
#40
0(
#45
b10110 0
b10110 7
b101 1
b101 8
b101 =
b100 3
b100 :
b100 ;
1(
#50
0(
#55
b11 3
b11 :
b11 ;
1(
#60
0(
#65
b10 3
b10 :
b10 ;
1(
#70
0(
#75
b1 3
b1 :
b1 ;
1(
#80
0(
#85
1$
b0 3
b0 :
b0 ;
1(
#86
b100 ,
#90
0(
#95
0$
b1111111111111111 3
b1111111111111111 :
b1111111111111111 ;
1(
#96
b100 -
b11 ,
#97
b100 ,
0&
0!
1%
