debouncing circuit/controlpath.v
module controlpath(q_load,q_dec,db_tick_output,db_level,sw,q_zero,clk,rst);
	input wire sw, clk, q_zero, rst;
	output reg q_dec, q_load, db_level, db_tick, db_tick_output;
	
	reg [1:0] state_reg, state_next;
	
	localparam [1:0] 
		zero = 2'b00,
		wait1 = 2'b01,
		one = 2'b10,
		wait0 = 2'b11;
	
	always @(posedge clk, posedge rst)
		begin
		if(rst)
			state_reg <= zero;
		else 
			state_reg <= state_next;
		end
	
	always @*
		begin
		state_next = state_reg;
		q_load = 1'b0;
		q_dec = 1'b0;
		db_tick = 1'b0;
		case(state_reg)
			zero:
				begin
				db_level = 1'b0;
				if(sw)
					begin
					state_next = wait1;
					q_load = 1'b1;
					end
				end
			wait1:
				begin
				db_level = 1'b0;
				if(~sw)
					begin
					state_next = zero;
					end
				else if(q_zero)
					begin
					state_next = one;
					db_tick = 1'b1;
					end
				else
					q_dec = 1'b1;
				end
			one:
				begin
				db_level = 1'b1;
				if(~sw)
					begin
					state_next = wait0;
					q_load = 1'b1;
					end
				end
			wait0:
				begin
				db_level = 1'b1;
				if(sw)
					state_next = one;
				else if(q_zero)
					state_next = zero;
				else 
					q_dec = 1'b1;
				end
			default: state_next = zero;
		endcase
		end
		
	always @(posedge clk, posedge rst)
		begin
		if(rst)
			db_tick_output <= 1'b0;
		else
			db_tick_output <= db_tick;
		end

endmodule

debouncing circuit/COMP.v
module COMP(out,in1,in2);
	localparam N = 3;
	input wire [N-1:0] in1, in2;
	output wire out;
	
	assign out = (in1 == in2);
endmodule

debouncing circuit/cntr.v
module CNTR(buf_out,load,dec,rst,clk);
	localparam N = 3;
	input wire load, dec, rst, clk;
	output wire [N-1:0] buf_out;

	reg [N-1:0] q_reg, q_next;
	
	assign buf_out = q_reg;
	
	always @(posedge clk, posedge rst)
		if(rst)	
			q_reg <= 0;
		else
			q_reg <= q_next;

	always @*
		if(load)
			q_next = {(N){1'b1}};
		else if(dec)
			q_next = q_reg - 1;
		else 
			q_next = q_reg;
endmodule

debouncing circuit/datapath.v
module datapath(q_zero,load,dec,rst,clk);
	localparam N = 3;
	input wire load, dec, rst, clk;
	output wire q_zero;
	
	wire [N-1:0] buf_out;
	wire [N-1:0] zero;
	
	assign zero = {(N){1'b0}} ;
	
	CNTR A(buf_out,load,dec,rst,clk);
	COMP B(q_zero,zero,buf_out);
endmodule

debouncing circuit/test_debounce.v
module test_debounce();
	reg clk, sw, rst;
	wire db_level, db_tick;
	
	wire q_zero, load, dec;
	
	datapath A(q_zero,load,dec,rst,clk);
	controlpath B(load,dec,db_tick,db_level,sw,q_zero,clk,rst);
	
	always #5 clk = ~clk;
	
	initial
		begin
		clk = 1'b0;
		rst = 1'b1;
		sw = 1'b0;
		
		@(negedge clk);
		
		rst = 1'b0;
		sw = 1'b1;
		
		repeat(11) @(negedge clk);
		
		sw = 1'b0;
		
		repeat(15) @(negedge clk);

		$finish;
		end
	
	initial
		begin
		$dumpfile("debounce.vcd");
		$dumpvars(0,test_debounce);
		end
endmodule

debouncing circuit/debounce.vcd
$date
	Sun Jan 10 00:34:49 2021
$end
$version
	Icarus Verilog
$end
$timescale
	1s
$end
$scope module test_debounce $end
$var wire 1 ! q_zero $end
$var wire 1 " load $end
$var wire 1 # dec $end
$var wire 1 $ db_tick $end
$var wire 1 % db_level $end
$var reg 1 & clk $end
$var reg 1 ' rst $end
$var reg 1 ( sw $end
$scope module A $end
$var wire 1 & clk $end
$var wire 1 ' rst $end
$var wire 3 ) zero [2:0] $end
$var wire 1 ! q_zero $end
$var wire 1 " load $end
$var wire 1 # dec $end
$var wire 3 * buf_out [2:0] $end
$scope module A $end
$var wire 1 & clk $end
$var wire 1 ' rst $end
$var wire 1 " load $end
$var wire 1 # dec $end
$var wire 3 + buf_out [2:0] $end
$var reg 3 , q_next [2:0] $end
$var reg 3 - q_reg [2:0] $end
$upscope $end
$scope module B $end
$var wire 3 . in1 [2:0] $end
$var wire 3 / in2 [2:0] $end
$var wire 1 ! out $end
$upscope $end
$upscope $end
$scope module B $end
$var wire 1 & clk $end
$var wire 1 ! q_zero $end
$var wire 1 ' rst $end
$var wire 1 ( sw $end
$var reg 1 % db_level $end
$var reg 1 0 db_tick $end
$var reg 1 $ db_tick_output $end
$var reg 1 # q_dec $end
$var reg 1 " q_load $end
$var reg 2 1 state_next [1:0] $end
$var reg 2 2 state_reg [1:0] $end
$upscope $end
$upscope $end
$enddefinitions $end
#0
$dumpvars
b0 2
b0 1
00
b0 /
b0 .
b0 -
b0 ,
b0 +
b0 *
b0 )
0(
1'
0&
0%
0$
0#
0"
1!
$end
#5
1&
#10
b111 ,
1"
b1 1
1(
0'
0&
#15
b110 ,
1#
0"
0!
b111 *
b111 +
b111 -
b111 /
b1 2
1&
#20
0&
#25
b101 ,
b110 *
b110 +
b110 -
b110 /
1&
#30
0&
#35
b100 ,
b101 *
b101 +
b101 -
b101 /
1&
#40
0&
#45
b11 ,
b100 *
b100 +
b100 -
b100 /
1&
#50
0&
#55
b10 ,
b11 *
b11 +
b11 -
b11 /
1&
#60
0&
#65
b1 ,
b10 *
b10 +
b10 -
b10 /
1&
#70
0&
#75
b0 ,
b1 *
b1 +
b1 -
b1 /
1&
#80
0&
#85
10
b10 1
0#
1!
b0 *
b0 +
b0 -
b0 /
1&
#90
0&
#95
1%
00
b10 2
1$
1&
#100
0&
#105
0$
1&
#110
0&
#115
1&
#120
b111 ,
1"
b11 1
0(
0&
#125
b110 ,
1#
0"
b11 2
0!
b111 *
b111 +
b111 -
b111 /
1&
#130
0&
#135
b101 ,
b110 *
b110 +
b110 -
b110 /
1&
#140
0&
#145
b100 ,
b101 *
b101 +
b101 -
b101 /
1&
#150
0&
#155
b11 ,
b100 *
b100 +
b100 -
b100 /
1&
#160
0&
#165
b10 ,
b11 *
b11 +
b11 -
b11 /
1&
#170
0&
#175
b1 ,
b10 *
b10 +
b10 -
b10 /
1&
#180
0&
#185
b0 ,
b1 *
b1 +
b1 -
b1 /
1&
#190
0&
#195
b0 1
0#
1!
b0 *
b0 +
b0 -
b0 /
1&
#200
0&
#205
0%
b0 2
1&
